mlexpy/__init__.py
mlexpy/defaultordereddict.py
mlexpy/experiment.py
mlexpy/pipeline_utils.py
mlexpy/processor.py
mlexpy/utils.py
mlexpy-0.0.2.dist-info/LICENSE
mlexpy-0.0.2.dist-info/METADATA
mlexpy-0.0.2.dist-info/WHEEL
mlexpy-0.0.2.dist-info/top_level.txt
mlexpy-0.0.2.dist-info/RECORD
