Metadata-Version: 2.1
Name: mlexpy
Version: 0.0.2
Summary: Simple utilities for handling and managing exploratory and experimental machine learning development.
Author-email: nesankar <nesankar@mtu.edu>
License: MIT License
Project-URL: Homepage, https://github.com/nesankar/mlexpy
Keywords: machine learning,ML,data science
Classifier: License :: OSI Approved :: MIT License
Classifier: Programming Language :: Python
Classifier: Programming Language :: Python :: 3
Classifier: Development Status :: 3 - Alpha
Classifier: Operating System :: OS Independent
Classifier: Intended Audience :: Science/Research
Classifier: Framework :: tox
Classifier: Natural Language :: English
Classifier: Topic :: Scientific/Engineering :: Artificial Intelligence
Classifier: Typing :: Typed
Requires-Python: >=3.9
License-File: LICENSE
Requires-Dist: scikit-learn
Requires-Dist: matplotlib
Requires-Dist: seaborn
Requires-Dist: pandas
Requires-Dist: numpy
Provides-Extra: dev
Requires-Dist: tox ; extra == 'dev'
Requires-Dist: black ; extra == 'dev'
Requires-Dist: mypy ; extra == 'dev'
